{
  "video_path": "/home/runner/work/goosebumps-Channel/goosebumps-Channel/output/20260509_062620_country.mp4",
  "mp3_path": "music/country/Milk Glass Window.mp3",
  "blueprint": {
    "genre": "Country",
    "title": "Milk Glass Window - Goosebumps Music",
    "frisson_score": 82,
    "scientific_note": "Engineered using the neuroscience of frisson to trigger goosebumps.",
    "description": "Milk Glass Window is crafted to give you chills using the science of musical frisson.\n\nSubscribe to the Goosebumps Channel for more.",
    "tags": [
      "goosebumps",
      "frisson",
      "country",
      "royalty free music",
      "chills"
    ]
  }
}